datasience_methods/__init__.py
datasience_methods/data_preprocessing/__init__.py
datasience_methods/utils/__init__.py
datasience_methods/utils/merging.py
datasience_methods-0.1.54.dist-info/LICENSE
datasience_methods-0.1.54.dist-info/METADATA
datasience_methods-0.1.54.dist-info/WHEEL
datasience_methods-0.1.54.dist-info/top_level.txt
datasience_methods-0.1.54.dist-info/RECORD
