Metadata-Version: 2.1
Name: datasience_methods
Version: 0.1.54
Summary: A collection of useful data science methods
Home-page: https://github.com/Bratet/datasience_methods
Author: Bratet
Author-email: ahmedmrabet.002@gmail.com
Classifier: Development Status :: 3 - Alpha
Classifier: Intended Audience :: Developers
Classifier: License :: OSI Approved :: MIT License
Classifier: Programming Language :: Python :: 3
Classifier: Programming Language :: Python :: 3.7
Classifier: Programming Language :: Python :: 3.8
Classifier: Programming Language :: Python :: 3.9
Requires-Python: >=3.7
License-File: LICENSE
Requires-Dist: pandas>=1.0.0
Requires-Dist: fuzzywuzzy>=0.18.0
Requires-Dist: python-Levenshtein>=0.12.0
Requires-Dist: jellyfish==0.9.0
Requires-Dist: scipy>=1.7
Provides-Extra: dev
Requires-Dist: pytest>=6.0; extra == "dev"
Requires-Dist: pytest-cov>=2.0; extra == "dev"
